lightquant/__init__.py
lightquant/config.py
lightquant/config_extra_fn.py
lightquant/dateutils.py
lightquant/europeanoptions.py
lightquant/interactions.py
lightquant/miscutils.py
lightquant/config/config_sample.yaml
lightquant-0.1.8.dist-info/licenses/LICENSE
tests/__init__.py
tests/conftest.py
tests/test_backtesting.py
tests/test_config.py
tests/test_data_loader.py
tests/test_execution.py
tests/test_indicators.py
lightquant-0.1.8.dist-info/METADATA
lightquant-0.1.8.dist-info/WHEEL
lightquant-0.1.8.dist-info/top_level.txt
lightquant-0.1.8.dist-info/RECORD
