Metadata-Version: 2.4
Name: lightquant
Version: 0.1.8
Summary: A lightweight Python library for python utilities for holidays, dates, options and other tools
Home-page: https://bitbucket.org/incurrency/lightquant
Author: Pankaj Sharma
Author-email: Pankaj Sharma <sharma.pankaj.kumar@gmail.com>
License: MIT License
Project-URL: homepage, https://github.com/yourusername/lightQuant
Project-URL: repository, https://github.com/yourusername/lightQuant
License-File: LICENSE
Requires-Dist: numpy==1.21.6
Requires-Dist: pandas==1.5.3
Requires-Dist: scikit-learn==1.5.0
Requires-Dist: scipy==1.11.4
Requires-Dist: pyyaml==6.0
Requires-Dist: pyreadr==0.5.0
Requires-Dist: rpy2==3.5.16
Requires-Dist: pytz==2024.1
Requires-Dist: selenium==4.0.0
Requires-Dist: requests==2.32.3
Requires-Dist: psutil==7.0.0
Dynamic: author
Dynamic: home-page
Dynamic: license-file
